{
  "Port": 9117,
  "AllowExternal": true,
  "AllowCORS": false,
  "APIKey": "g2l8aplaaexyyeb96ta1th9znue2t0sf",
  "AdminPassword": null,
  "InstanceId": "pxioeyq531airogp6mgm4yk8wtt9ft9oy2dmksif1qqp21wbruoueexxdfc2owd9",
  "BlackholeDir": "",
  "UpdateDisabled": false,
  "UpdatePrerelease": false,
  "BasePathOverride": "",
  "BaseUrlOverride": "",
  "CacheEnabled": true,
  "CacheTtl": 2100,
  "CacheMaxResultsPerIndexer": 1000,
  "FlareSolverrUrl": "http://172.128.2.13:8191",
  "FlareSolverrMaxTimeout": 55000,
  "OmdbApiKey": "",
  "OmdbApiUrl": "",
  "ProxyType": -1,
  "ProxyUrl": "",
  "ProxyPort": null,
  "ProxyUsername": "",
  "ProxyPassword": "",
  "ProxyIsAnonymous": true
}